opentelemetry/processor/baggage/__init__.py
opentelemetry/processor/baggage/processor.py
opentelemetry/processor/baggage/version.py
opentelemetry_processor_baggage-0.60b1.dist-info/METADATA
opentelemetry_processor_baggage-0.60b1.dist-info/WHEEL
opentelemetry_processor_baggage-0.60b1.dist-info/licenses/LICENSE
opentelemetry_processor_baggage-0.60b1.dist-info/RECORD
