Metadata-Version: 2.4
Name: opentelemetry-processor-baggage
Version: 0.60b1
Summary: OpenTelemetry Baggage Span Processor
Project-URL: Homepage, https://github.com/open-telemetry/opentelemetry-python-contrib/tree/main/processor/opentelemetry-processor-baggage
Project-URL: Repository, https://github.com/open-telemetry/opentelemetry-python-contrib
Author-email: OpenTelemetry Authors <cncf-opentelemetry-contributors@lists.cncf.io>
License-Expression: Apache-2.0
License-File: LICENSE
Classifier: Development Status :: 4 - Beta
Classifier: Intended Audience :: Developers
Classifier: License :: OSI Approved :: Apache Software License
Classifier: Programming Language :: Python
Classifier: Programming Language :: Python :: 3
Classifier: Programming Language :: Python :: 3.9
Classifier: Programming Language :: Python :: 3.10
Classifier: Programming Language :: Python :: 3.11
Classifier: Programming Language :: Python :: 3.12
Classifier: Programming Language :: Python :: 3.13
Requires-Python: >=3.9
Requires-Dist: opentelemetry-api~=1.5
Requires-Dist: opentelemetry-sdk~=1.5
Requires-Dist: wrapt<2.0.0,>=1.0.0
